tti_power_supply/__init__.py
tti_power_supply/driver.py
tti_power_supply/simulation.py
tti_power_supply/sipyco_controller.py
tti_power_supply/tcp_driver.py
tti_power_supply/usb_driver.py
tti_power_supply-1.0.2.dist-info/METADATA
tti_power_supply-1.0.2.dist-info/WHEEL
tti_power_supply-1.0.2.dist-info/entry_points.txt
tti_power_supply-1.0.2.dist-info/RECORD
